matrix_client/__init__.py
matrix_client/api.py
matrix_client/checks.py
matrix_client/client.py
matrix_client/device.py
matrix_client/errors.py
matrix_client/room.py
matrix_client/user.py
matrix_client/crypto/__init__.py
matrix_client/crypto/crypto_store.py
matrix_client/crypto/device_list.py
matrix_client/crypto/encrypt_attachments.py
matrix_client/crypto/key_export.py
matrix_client/crypto/key_sharing.py
matrix_client/crypto/olm_device.py
matrix_client/crypto/one_time_keys.py
matrix_client/crypto/sessions.py
matrix_client/crypto/verified_event.py
matrix_client_harmonyqt-0.4.2.dev5.dist-info/LICENSE.txt
matrix_client_harmonyqt-0.4.2.dev5.dist-info/METADATA
matrix_client_harmonyqt-0.4.2.dev5.dist-info/RECORD
matrix_client_harmonyqt-0.4.2.dev5.dist-info/WHEEL
matrix_client_harmonyqt-0.4.2.dev5.dist-info/top_level.txt
test/__init__.py
test/api_test.py
test/client_test.py
test/device_test.py
test/response_examples.py
test/user_test.py
test/crypto/__init__.py
test/crypto/crypto_store_test.py
test/crypto/device_list_test.py
test/crypto/dummy_olm_device.py
test/crypto/encrypted_attachments_test.py
test/crypto/key_export_test.py
test/crypto/key_sharing_test.py
test/crypto/olm_device_test.py
