Metadata-Version: 2.1
Name: matrix-client-harmonyqt
Version: 0.4.2.dev5
Summary: Client-Server SDK for Matrix - development fork
Home-page: https://github.com/matrix-org/matrix-python-sdk
Author: The Matrix.org Team
Author-email: team@matrix.org
License: Apache License, Version 2.0
Keywords: chat sdk matrix matrix.org
Platform: UNKNOWN
Classifier: Development Status :: 3 - Alpha
Classifier: Intended Audience :: Developers
Classifier: License :: OSI Approved :: Apache Software License
Classifier: Programming Language :: Python :: 2
Classifier: Programming Language :: Python :: 3
Classifier: Topic :: Communications :: Chat
Classifier: Topic :: Communications :: Conferencing
Provides-Extra: e2e
Provides-Extra: format
Provides-Extra: test
Provides-Extra: doc
Requires-Dist: requests
Requires-Dist: urllib3
Provides-Extra: doc
Requires-Dist: Sphinx (==1.4.6); extra == 'doc'
Requires-Dist: sphinx-rtd-theme (==0.1.9); extra == 'doc'
Requires-Dist: sphinxcontrib-napoleon (==0.5.3); extra == 'doc'
Provides-Extra: e2e
Requires-Dist: python-olm-harmonyqt (>=0.1); extra == 'e2e'
Requires-Dist: canonicaljson; extra == 'e2e'
Requires-Dist: appdirs; extra == 'e2e'
Requires-Dist: unpaddedbase64; extra == 'e2e'
Requires-Dist: pycrypto; extra == 'e2e'
Requires-Dist: future (>=0.17.1); extra == 'e2e'
Provides-Extra: format
Requires-Dist: flake8; extra == 'format'
Provides-Extra: test
Requires-Dist: pytest; extra == 'test'
Requires-Dist: responses; extra == 'test'
